<?xml version="1.0" encoding="UTF-8" ?>
<!DOCTYPE mapper PUBLIC "-//mybatis.org//DTD Mapper 3.0//EN" "http://mybatis.org/dtd/mybatis-3-mapper.dtd" >
<mapper namespace="com.creditharmony.approve.phone.dao.DhzhDhgxbrshdDao" >
  <resultMap id="BaseResultMap" type="com.creditharmony.approve.phone.entity.DhzhDhgxbrshd" >
    <!--
      WARNING - @mbggenerated
      This element is automatically generated by MyBatis Generator, do not modify.
      This element was generated on Wed Mar 02 20:17:30 CST 2016.
    -->
    <id column="id" property="id" jdbcType="VARCHAR" />
    <result column="r_customer_coborrower_id" property="rCustomerCoborrowerId" jdbcType="VARCHAR" />
    <result column="live_province" property="liveProvince" jdbcType="VARCHAR" />
    <result column="live_city" property="liveCity" jdbcType="VARCHAR" />
    <result column="live_area" property="liveArea" jdbcType="VARCHAR" />
    <result column="live_address" property="liveAddress" jdbcType="VARCHAR" />
    <result column="is_repeat" property="isRepeat" jdbcType="VARCHAR" />
    <result column="is_in_pool" property="isInPool" jdbcType="VARCHAR" />
    <result column="loan_id" property="loanId" jdbcType="VARCHAR" />
    <result column="create_by" property="createBy" jdbcType="VARCHAR" />
    <result column="create_time" property="createTime" jdbcType="TIMESTAMP" />
    <result column="modify_time" property="modifyTime" jdbcType="TIMESTAMP" />
    <result column="modify_by" property="modifyBy" jdbcType="VARCHAR" />
    <result column="edit_remark" property="editRemark" jdbcType="CHAR" />
  </resultMap>
  
  <sql id="Base_Column_List" >
    <!--
      WARNING - @mbggenerated
      This element is automatically generated by MyBatis Generator, do not modify.
      This element was generated on Wed Mar 02 20:17:30 CST 2016.
    -->
    id, r_customer_coborrower_id, live_province, live_city, live_area, live_address, net_check_result, net_check_remark,
    is_repeat, is_in_pool, loan_id, create_by, create_time, modify_time, modify_by, edit_remark
  </sql>
  <select id="selectByPrimaryKey" resultMap="BaseResultMap" parameterType="java.lang.String" >
    <!--
      WARNING - @mbggenerated
      This element is automatically generated by MyBatis Generator, do not modify.
      This element was generated on Wed Mar 02 20:17:30 CST 2016.
    -->
    select 
    <include refid="Base_Column_List" />
    from jk.t_jk_dhzh_dhgxbrshd
    where id = #{id,jdbcType=VARCHAR}
  </select>
  <delete id="deleteByPrimaryKey" parameterType="java.lang.String" >
    <!--
      WARNING - @mbggenerated
      This element is automatically generated by MyBatis Generator, do not modify.
      This element was generated on Wed Mar 02 20:17:30 CST 2016.
    -->
    delete from jk.t_jk_dhzh_dhgxbrshd
    where id = #{id,jdbcType=VARCHAR}
  </delete>
  <insert id="insert" parameterType="com.creditharmony.approve.phone.entity.DhzhDhgxbrshd" >
    <!--
      WARNING - @mbggenerated
      This element is automatically generated by MyBatis Generator, do not modify.
      This element was generated on Wed Mar 02 20:17:30 CST 2016.
    -->
    insert into jk.t_jk_dhzh_dhgxbrshd (id, r_customer_coborrower_id, live_province, 
      live_city, live_area, live_address, net_check_result, net_check_remark,
      is_repeat, is_in_pool, create_by, create_time, modify_time, modify_by, 
      edit_remark, loan_id)
    values (#{id,jdbcType=VARCHAR}, #{rCustomerCoborrowerId,jdbcType=VARCHAR}, #{liveProvince,jdbcType=VARCHAR}, 
      #{liveCity,jdbcType=VARCHAR}, #{liveArea,jdbcType=VARCHAR}, #{liveAddress,jdbcType=VARCHAR}, 
      #{netCheckResult,jdbcType=VARCHAR}, #{netCheckRemark,jdbcType=VARCHAR}, 
      #{isRepeat,jdbcType=VARCHAR}, #{isInPool,jdbcType=VARCHAR}, #{createBy,jdbcType=VARCHAR}, 
      #{createTime,jdbcType=TIMESTAMP}, #{modifyTime,jdbcType=TIMESTAMP}, #{modifyBy,jdbcType=VARCHAR}, 
      #{editRemark,jdbcType=CHAR}, #{loanId,jdbcType=CHAR})
  </insert>
  <insert id="insertSelective" parameterType="com.creditharmony.approve.phone.entity.DhzhDhgxbrshd" >
    <!--
      WARNING - @mbggenerated
      This element is automatically generated by MyBatis Generator, do not modify.
      This element was generated on Wed Mar 02 20:17:30 CST 2016.
    -->
    insert into jk.t_jk_dhzh_dhgxbrshd
    <trim prefix="(" suffix=")" suffixOverrides="," >
      <if test="id != null" >
        id,
      </if>
      <if test="rCustomerCoborrowerId != null" >
        r_customer_coborrower_id,
      </if>
      <if test="liveProvince != null" >
        live_province,
      </if>
      <if test="liveCity != null" >
        live_city,
      </if>
      <if test="liveArea != null" >
        live_area,
      </if>
      <if test="liveAddress != null" >
        live_address,
      </if>
      <if test="isRepeat != null" >
        is_repeat,
      </if>
      <if test="isInPool != null" >
        is_in_pool,
      </if>
      <if test="loanId != null" >
        loan_id,
      </if>
      <if test="createBy != null" >
        create_by,
      </if>
      <if test="createTime != null" >
        create_time,
      </if>
      <if test="modifyTime != null" >
        modify_time,
      </if>
      <if test="modifyBy != null" >
        modify_by,
      </if>
      <if test="editRemark != null" >
        edit_remark,
      </if>
    </trim>
    <trim prefix="values (" suffix=")" suffixOverrides="," >
      <if test="id != null" >
        #{id,jdbcType=VARCHAR},
      </if>
      <if test="rCustomerCoborrowerId != null" >
        #{rCustomerCoborrowerId,jdbcType=VARCHAR},
      </if>
      <if test="liveProvince != null" >
        #{liveProvince,jdbcType=VARCHAR},
      </if>
      <if test="liveCity != null" >
        #{liveCity,jdbcType=VARCHAR},
      </if>
      <if test="liveArea != null" >
        #{liveArea,jdbcType=VARCHAR},
      </if>
      <if test="liveAddress != null" >
        #{liveAddress,jdbcType=VARCHAR},
      </if>
      <if test="isRepeat != null" >
        #{isRepeat,jdbcType=VARCHAR},
      </if>
      <if test="isInPool != null" >
        #{isInPool,jdbcType=VARCHAR},
      </if>
      <if test="loanId != null" >
        #{loanId,jdbcType=VARCHAR},
      </if>
      <if test="createBy != null" >
        #{createBy,jdbcType=VARCHAR},
      </if>
      <if test="createTime != null" >
        #{createTime,jdbcType=TIMESTAMP},
      </if>
      <if test="modifyTime != null" >
        #{modifyTime,jdbcType=TIMESTAMP},
      </if>
      <if test="modifyBy != null" >
        #{modifyBy,jdbcType=VARCHAR},
      </if>
      <if test="editRemark != null" >
        #{editRemark,jdbcType=CHAR},
      </if>
    </trim>
  </insert>
  <update id="updateByPrimaryKeySelective" parameterType="com.creditharmony.approve.phone.entity.DhzhDhgxbrshd" >
    <!--
      WARNING - @mbggenerated
      This element is automatically generated by MyBatis Generator, do not modify.
      This element was generated on Wed Mar 02 20:17:30 CST 2016.
    -->
    update jk.t_jk_dhzh_dhgxbrshd
    <set >
      <if test="rCustomerCoborrowerId != null" >
        r_customer_coborrower_id = #{rCustomerCoborrowerId,jdbcType=VARCHAR},
      </if>
      <if test="liveProvince != null" >
        live_province = #{liveProvince,jdbcType=VARCHAR},
      </if>
      <if test="liveCity != null" >
        live_city = #{liveCity,jdbcType=VARCHAR},
      </if>
      <if test="liveArea != null" >
        live_area = #{liveArea,jdbcType=VARCHAR},
      </if>
      <if test="liveAddress != null" >
        live_address = #{liveAddress,jdbcType=VARCHAR},
      </if>
      <if test="isRepeat != null" >
        is_repeat = #{isRepeat,jdbcType=VARCHAR},
      </if>
      <if test="isInPool != null" >
        is_in_pool = #{isInPool,jdbcType=VARCHAR},
      </if>
      <if test="createBy != null" >
        create_by = #{createBy,jdbcType=VARCHAR},
      </if>
      <if test="createTime != null" >
        create_time = #{createTime,jdbcType=TIMESTAMP},
      </if>
      <if test="modifyTime != null" >
        modify_time = #{modifyTime,jdbcType=TIMESTAMP},
      </if>
      <if test="modifyBy != null" >
        modify_by = #{modifyBy,jdbcType=VARCHAR},
      </if>
      <if test="editRemark != null" >
        edit_remark = #{editRemark,jdbcType=CHAR},
      </if>
      <if test="netCheckResult != null" >
        net_check_result = #{netCheckResult,jdbcType=VARCHAR},
      </if>
      <if test="netCheckRemark != null" >
        net_check_remark = #{netCheckRemark,jdbcType=VARCHAR},
      </if>
    </set>
    where id = #{id,jdbcType=VARCHAR}
  </update>
  <update id="updateByPrimaryKey" parameterType="com.creditharmony.approve.phone.entity.DhzhDhgxbrshd" >
    <!--
      WARNING - @mbggenerated
      This element is automatically generated by MyBatis Generator, do not modify.
      This element was generated on Wed Mar 02 20:17:30 CST 2016.
    -->
    update jk.t_jk_dhzh_dhgxbrshd
    set r_customer_coborrower_id = #{rCustomerCoborrowerId,jdbcType=VARCHAR},
      live_province = #{liveProvince,jdbcType=VARCHAR},
      live_city = #{liveCity,jdbcType=VARCHAR},
      live_area = #{liveArea,jdbcType=VARCHAR},
      live_address = #{liveAddress,jdbcType=VARCHAR},
      is_repeat = #{isRepeat,jdbcType=VARCHAR},
      is_in_pool = #{isInPool,jdbcType=VARCHAR},
      create_by = #{createBy,jdbcType=VARCHAR},
      create_time = #{createTime,jdbcType=TIMESTAMP},
      modify_time = #{modifyTime,jdbcType=TIMESTAMP},
      modify_by = #{modifyBy,jdbcType=VARCHAR},
      edit_remark = #{editRemark,jdbcType=CHAR}
    where id = #{id,jdbcType=VARCHAR}
  </update>
	<!-- 查询本人居住地址 -->
	<select id="getByRid" parameterType="java.lang.String" resultType="com.creditharmony.approve.phone.entity.DhzhDhgxbrshd" >
		select 
			<include refid="Base_Column_List" />
		from
			jk.t_jk_dhzh_dhgxbrshd
		where
			r_customer_coborrower_id = #{rId,jdbcType=VARCHAR}
	</select>
  
  <update id="updateByList" parameterType="java.util.Map">
	  <foreach collection="address" item="item" separator=";">
	  		UPDATE JK.T_JK_DHZH_DHGXBRSHD SET NET_CHECK_RESULT = #{item.netCheckResult},
	  		NET_CHECK_REMARK = #{item.netCheckRemark} 
	  		WHERE ID = #{item.id}
	  </foreach>
  </update>
  
  
</mapper>